cdci_osa_plugin/__init__.py
cdci_osa_plugin/exposer.py
cdci_osa_plugin/osa_catalog.py
cdci_osa_plugin/osa_common_pars.py
cdci_osa_plugin/osa_dataserve_dispatcher.py
cdci_osa_plugin/osa_fake.py
cdci_osa_plugin/osa_image_query.py
cdci_osa_plugin/osa_isgri.py
cdci_osa_plugin/osa_jemx.py
cdci_osa_plugin/osa_lightcurve_query.py
cdci_osa_plugin/osa_spectrum_query.py
cdci_osa_plugin/config_dir/data_server_conf.yml
cdci_osa_plugin/tests/test_osa.py
dispatcher_plugin_integral-1.0.dist-info/LICENSE.rst
dispatcher_plugin_integral-1.0.dist-info/METADATA
dispatcher_plugin_integral-1.0.dist-info/WHEEL
dispatcher_plugin_integral-1.0.dist-info/top_level.txt
dispatcher_plugin_integral-1.0.dist-info/RECORD
