Metadata-Version: 2.1
Name: dispatcher-plugin-integral
Version: 1.0
Summary: A  OSA plugin  for CDCI online data analysis
Home-page: UNKNOWN
Author: Andrea Tramacere
Author-email: andrea.tramacere@unige.ch
License: UNKNOWN
Platform: UNKNOWN
Requires-Dist: ddaclient
Requires-Dist: oda-knowledge-base[cwl,rdf]
